pdcscore/__init__.py
pdcscore/pdcscore.py
pdcscore-1.1.9.dist-info/LICENSE
pdcscore-1.1.9.dist-info/METADATA
pdcscore-1.1.9.dist-info/WHEEL
pdcscore-1.1.9.dist-info/top_level.txt
pdcscore-1.1.9.dist-info/RECORD
