Metadata-Version: 2.1
Name: pdcscore
Version: 1.1.9
Summary: A package to facilitate efficient and accurate calculation of the medication adherence metric "Proportion of Days Covered" or "PDC".
Home-page: https://github.com/famutimine/pdcscore
Author: Daniel Famutimi MD, MPH
Author-email: danielfamutimi@gmail.com
License: MIT
Keywords: pdc calculator medication adherence
Platform: UNKNOWN
Classifier: Development Status :: 5 - Production/Stable
Classifier: Intended Audience :: Developers
Classifier: Intended Audience :: Healthcare Industry
Classifier: Intended Audience :: System Administrators
Classifier: License :: OSI Approved :: MIT License
Classifier: Programming Language :: Python :: 3
Classifier: Programming Language :: Python :: 3.6
Classifier: Programming Language :: Python :: 3.7
Classifier: Programming Language :: Python :: 3.8
Classifier: Programming Language :: Python :: 3.9
Classifier: Topic :: Software Development :: Libraries :: Python Modules
Classifier: Topic :: Scientific/Engineering :: Medical Science Apps.
Classifier: Topic :: Scientific/Engineering :: Information Analysis
License-File: LICENSE
Requires-Dist: numpy
Requires-Dist: pandas
